{
    "_id": "1",
    "name": "鸡爪",
    "unit": "500g",
    "price": 5.0,
    "fileId": "cloud://dev-o45qm.6465-dev-o45qm-1301624908/goods-list/10141584450128_.pic.jpg",
    "desc": "很好吃的鸡爪1",
    "tag": "爆款促销",
    "num": 10,
    "originPrice": 4.99
}
{
    "_id": "2",
    "name": "鸡爪",
    "unit": "500g",
    "price": 5.0,
    "fileId": "cloud://dev-o45qm.6465-dev-o45qm-1301624908/goods-list/10141584450128_.pic.jpg",
    "desc": "很好吃的鸡爪2",
    "tag": "爆款促销",
    "num": 10,
    "originPrice": 4.99
}